Metadata-Version: 1.0
Name: brick-house-cli
Version: 0.1
Summary: Calculate a brick house
Home-page: UNKNOWN
Author: Mike Panikovsky
Author-email: flyingcircus@example.com
License: MIT
Platform: UNKNOWN
